redlock_dist/__init__.py
redlock_dist/redlock.py
redlock_dist-1.0.1.dist-info/METADATA
redlock_dist-1.0.1.dist-info/RECORD
redlock_dist-1.0.1.dist-info/WHEEL
redlock_dist-1.0.1.dist-info/top_level.txt
