Metadata-Version: 2.1
Name: redlock-dist
Version: 1.0.1
Summary: Distributed locks with Redis
Home-page: https://github.com/kerol/redlock-dist
Author: kerol
Author-email: ikerol@163.com
License: UNKNOWN
Platform: UNKNOWN
Classifier: License :: OSI Approved :: MIT License
Classifier: Operating System :: OS Independent
Classifier: Programming Language :: Python :: 3.6
Requires-Dist: redis (>=2.10.6)
